README.rst
setup.py
pyark/__init__.py
pyark/version.py
pyark.egg-info/PKG-INFO
pyark.egg-info/SOURCES.txt
pyark.egg-info/dependency_links.txt
pyark.egg-info/entry_points.txt
pyark.egg-info/requires.txt
pyark.egg-info/top_level.txt