Metadata-Version: 1.1
Name: pyark
Version: 1.1.1
Summary: Pyark is a small python-based CLI tool, which allows you to interact with the CyberArk Enterprise Password Vault API.
Home-page: https://github.com/adfinis-sygroup/pyark
Author: Adfinis SyGroup AG
Author-email: info@adfinis-sygroup.ch
License: UNKNOWN
Keywords: CyberArk,Password Vault,API,CLI
Platform: UNKNOWN
Classifier: Development Status :: 5 - Production/Stable
Classifier: Environment :: Console
Classifier: Intended Audience :: Developers
Classifier: Intended Audience :: System Administrators
Classifier: Intended Audience :: Information Technology
Classifier: License :: OSI Approved :: GNU General Public License v3 (GPLv3)
Classifier: Natural Language :: English
Classifier: Operating System :: OS Independent
Classifier: Programming Language :: Python :: 3.5
Classifier: Topic :: System :: Systems Administration :: Authentication/Directory
